GlobalKit/__init__.py
GlobalKit/alphabet.py
GlobalKit/functions.py
GlobalKit/main.py
globalkit-1.7.dist-info/WHEEL
globalkit-1.7.dist-info/METADATA
globalkit-1.7.dist-info/RECORD
