Metadata-Version: 2.1
Name: GlobalKit
Version: 1.7
Summary: Get alphabets from various languages and a set of functions for text manipulation
Author-email: CrazyFlyKite <karpenkoartem2846@gmail.com>
Requires-Python: >=3.11
Classifier: Development Status :: 5 - Production/Stable
Classifier: License :: OSI Approved :: MIT License
Classifier: Intended Audience :: Developers
Classifier: Topic :: Software Development :: Libraries :: Python Modules
Project-URL: Bug-Tracker, https://github.com/CrazyFlyKite/GlobalKit/issues
Project-URL: PyPI, https://pypi.org/project/GlobalKit
Project-URL: Repository, https://github.com/CrazyFlyKite/GlobalKit
